LICENSE
MANIFEST.in
README.md
setup.cfg
setup.py
attachment/__init__.py
attachment/admin.py
attachment/apps.py
attachment/base_admin.py
attachment/base_models.py
attachment/models.py
attachment/permissions.py
attachment/serializers.py
attachment/urls.py
attachment/utils.py
attachment/views.py
attachment/viewsets.py
attachment/migrations/0001_initial.py
attachment/migrations/__init__.py
django_rest_attachment.egg-info/PKG-INFO
django_rest_attachment.egg-info/SOURCES.txt
django_rest_attachment.egg-info/dependency_links.txt
django_rest_attachment.egg-info/top_level.txt
docs/.DS_Store
docs/README.md
docs/media/image-20200511175743782.png
docs/media/post-attachment-body.png
docs/media/post-attachment-header.png