Metadata-Version: 2.1
Name: django-rest-attachment
Version: 0.2
Summary: A Django app providing simple rest attachment upload and download.
Home-page: https://www.example.com/
Author: Chunkai Meng
Author-email: yourname@example.com
License: BSD-3-Clause
Platform: UNKNOWN
Classifier: Environment :: Web Environment
Classifier: Framework :: Django
Classifier: Framework :: Django :: 2.2
Classifier: Intended Audience :: Developers
Classifier: License :: OSI Approved :: BSD License
Classifier: Operating System :: OS Independent
Classifier: Programming Language :: Python :: 3.7
